lsst/ctrl/bps/htcondor/__init__.py
lsst/ctrl/bps/htcondor/common_utils.py
lsst/ctrl/bps/htcondor/dagman_configurator.py
lsst/ctrl/bps/htcondor/final_post.sh
lsst/ctrl/bps/htcondor/handlers.py
lsst/ctrl/bps/htcondor/htcondor_config.py
lsst/ctrl/bps/htcondor/htcondor_service.py
lsst/ctrl/bps/htcondor/htcondor_workflow.py
lsst/ctrl/bps/htcondor/lssthtc.py
lsst/ctrl/bps/htcondor/prepare_utils.py
lsst/ctrl/bps/htcondor/provisioner.py
lsst/ctrl/bps/htcondor/report_utils.py
lsst/ctrl/bps/htcondor/version.py
lsst/ctrl/bps/htcondor/etc/__init__.py
lsst/ctrl/bps/htcondor/etc/htcondor_defaults.yaml
lsst_ctrl_bps_htcondor-30.2026.300.dist-info/licenses/COPYRIGHT
lsst_ctrl_bps_htcondor-30.2026.300.dist-info/licenses/LICENSE
lsst_ctrl_bps_htcondor-30.2026.300.dist-info/licenses/bsd_license.txt
lsst_ctrl_bps_htcondor-30.2026.300.dist-info/licenses/gpl-v3.0.txt
lsst_ctrl_bps_htcondor-30.2026.300.dist-info/METADATA
lsst_ctrl_bps_htcondor-30.2026.300.dist-info/WHEEL
lsst_ctrl_bps_htcondor-30.2026.300.dist-info/top_level.txt
lsst_ctrl_bps_htcondor-30.2026.300.dist-info/zip-safe
lsst_ctrl_bps_htcondor-30.2026.300.dist-info/RECORD
